verif_token/__init__.py
verif_token/config.py
verif_token/verif_token.py
verif_token-0.2.3.dist-info/LICENSE
verif_token-0.2.3.dist-info/METADATA
verif_token-0.2.3.dist-info/WHEEL
verif_token-0.2.3.dist-info/top_level.txt
verif_token-0.2.3.dist-info/RECORD
