Metadata-Version: 2.2
Name: verif_token
Version: 0.2.3
Summary: Koden tool for verify the Token
Author-email: Sébastien Héligon <heligon.seb@gmail.com>
License:                                  Apache License
Project-URL: Homepage, https://github.com/koden-process/verif-token-lib
Project-URL: Repository, https://github.com/koden-process/verif-token-lib
Classifier: Programming Language :: Python :: 3
Classifier: License :: OSI Approved :: Apache Software License
Classifier: Operating System :: OS Independent
Requires-Python: >=3.12
License-File: LICENSE
Requires-Dist: requests~=2.31.0
Requires-Dist: fastapi~=0.104.1
Requires-Dist: python-jose~=3.3.0
